quicly
