Metadata-Version: 2.2
Name: quicly
Version: 1.0.91
Home-page: https://pypi.org/project/quicly/
Author: ziyue0
Author-email: ziyue0@gmail.com
Keywords: quicly
Classifier: Programming Language :: Python :: 3
Classifier: Programming Language :: Python :: 3.6
Classifier: Programming Language :: Python :: 3.6
Classifier: Programming Language :: Python :: 3.7
Classifier: Programming Language :: Python :: 3.8
Classifier: Programming Language :: Python :: 3.9
Classifier: Programming Language :: Python :: 3.10
Classifier: Programming Language :: Python :: 3.11
Classifier: Programming Language :: Python :: 3.12
Classifier: License :: OSI Approved :: MIT License
Classifier: Operating System :: OS Independent
Requires-Dist: requests
Requires-Dist: pymongo
Requires-Dist: redis
Requires-Dist: pyyaml
Requires-Dist: bson
Requires-Dist: pydes
Requires-Dist: flask
Requires-Dist: jinja2
Requires-Dist: cached-property
Dynamic: author
Dynamic: author-email
Dynamic: classifier
Dynamic: description-content-type
Dynamic: home-page
Dynamic: keywords
Dynamic: requires-dist
